BrokenFFmpeg/__init__.py
BrokenFFmpeg/BrokenFFmpeg.py
broken_ffmpeg-2024.1.15.dist-info/License.md
broken_ffmpeg-2024.1.15.dist-info/METADATA
broken_ffmpeg-2024.1.15.dist-info/WHEEL
broken_ffmpeg-2024.1.15.dist-info/RECORD
