Metadata-Version: 2.1
Name: broken-ffmpeg
Version: 2024.1.15
Summary: Your Premium Fluent FFmpeg class. Safely bundle, build and run FFmpeg commands
Home-page: https://github.com/BrokenSource/BrokenFFmpeg
License: MIT
Author: Tremeschin
Author-email: tremeschin@users.noreply.github.com
Requires-Python: >=3.10,<3.13
Classifier: License :: OSI Approved :: MIT License
Classifier: Programming Language :: Python :: 3
Classifier: Programming Language :: Python :: 3.10
Classifier: Programming Language :: Python :: 3.11
Classifier: Programming Language :: Python :: 3.12
Provides-Extra: all
Provides-Extra: bundled
Requires-Dist: attrs (>=23.2.0,<24.0.0)
Requires-Dist: broken-enum (>=2024.1.15,<2025.0.0)
Requires-Dist: imageio-ffmpeg (>=0.4.9,<0.5.0) ; extra == "all" or extra == "bundled"
Project-URL: Documentation, https://github.com/BrokenSource/BrokenFFmpeg
Project-URL: Repository, https://github.com/BrokenSource/BrokenFFmpeg
